stcrestclient/__init__.py
stcrestclient/adapt.py
stcrestclient/resthttp.py
stcrestclient/stchttp.py
stcrestclient/stcpythonrest.py
stcrestclient/systeminfo.py
stcrestclient/tccsh.py
stcrestclient-1.9.3.dist-info/LICENSE
stcrestclient-1.9.3.dist-info/METADATA
stcrestclient-1.9.3.dist-info/WHEEL
stcrestclient-1.9.3.dist-info/entry_points.txt
stcrestclient-1.9.3.dist-info/top_level.txt
stcrestclient-1.9.3.dist-info/zip-safe
stcrestclient-1.9.3.dist-info/RECORD
