Metadata-Version: 2.1
Name: stcrestclient
Version: 1.9.3
Summary: stcrestclient: Client modules for STC ReST API
Home-page: https://github.com/Spirent/py-stcrestclient
Author: Spirent
Author-email: support@spirent.com
License: http://www.opensource.org/licenses/mit-license.php
Keywords: Spirent TestCenter API
Classifier: Development Status :: 5 - Production/Stable
Classifier: Intended Audience :: Developers
Classifier: License :: OSI Approved :: MIT License
Classifier: Operating System :: POSIX
Classifier: Operating System :: Microsoft :: Windows
Classifier: Operating System :: MacOS :: MacOS X
Classifier: Topic :: Software Development :: Libraries
Classifier: Topic :: Utilities
Classifier: Programming Language :: Python
Classifier: Programming Language :: Python :: 2.7
Classifier: Programming Language :: Python :: 3
License-File: LICENSE
Requires-Dist: requests >=2.7
